nlp_text_corrector/__init__.py
nlp_text_corrector/asr_post_process.py
nlp_text_corrector-0.0.3.dist-info/LICENSE
nlp_text_corrector-0.0.3.dist-info/METADATA
nlp_text_corrector-0.0.3.dist-info/WHEEL
nlp_text_corrector-0.0.3.dist-info/top_level.txt
nlp_text_corrector-0.0.3.dist-info/RECORD
