Metadata-Version: 2.1
Name: nlp-text-corrector
Version: 0.0.3
Summary: IAMAI ASR Post Process Library
Home-page: https://github.com/iAmPlus/nlp-text-corrector
Author: Manoj Preveen
Author-email: manoj.velusamy@iamplus.com
License: MIT
Platform: UNKNOWN
License-File: LICENSE
